Metadata-Version: 1.0
Name: csc440-albertm1-stage-a
Version: 1.4
Summary: User creation and deletion methods for a Flask wiki app
Home-page: UNKNOWN
Author: Matthew Albert
Author-email: albertm1@nku.edu
License: UNKNOWN
Platform: UNKNOWN
